spline_agent/__init__.py
spline_agent/commons/__init__.py
spline_agent/commons/configuration/__init__.py
spline_agent/commons/configuration/base_configuration.py
spline_agent/commons/configuration/composite_configuration.py
spline_agent/commons/configuration/configuration.py
spline_agent/commons/configuration/dict_configuration.py
spline_agent/commons/configuration/dynaconf_configuration.py
spline_agent/commons/configuration/env_configuration.py
spline_agent/commons/configuration/file_configuration.py
spline_agent/commons/proxy.py
spline_agent/commons/utils.py
spline_agent/constants.py
spline_agent/context.py
spline_agent/datasources.py
spline_agent/decorators/__init__.py
spline_agent/decorators/io_decorators.py
spline_agent/decorators/model.py
spline_agent/decorators/spel_evaluator.py
spline_agent/decorators/track_lineage_decorator.py
spline_agent/dispatcher.py
spline_agent/dispatchers/__init__.py
spline_agent/dispatchers/console_dispatcher.py
spline_agent/dispatchers/http_dispatcher.py
spline_agent/dispatchers/logging_dispatcher.py
spline_agent/enums.py
spline_agent/exceptions.py
spline_agent/harvester.py
spline_agent/json_serde.py
spline_agent/lineage_model.py
spline_agent/object_factory.py
spline_agent/spline.default.yaml
spline_agent-0.1.2.dist-info/LICENSE
spline_agent-0.1.2.dist-info/METADATA
spline_agent-0.1.2.dist-info/WHEEL
spline_agent-0.1.2.dist-info/RECORD
