Metadata-Version: 2.1
Name: spline-agent
Version: 0.1.2
Summary: Spline agent for Python. Lineage tracking utility.
Home-page: https://github.com/AbsaOSS/spline-python-agent
License: Apache-2.0
Author: Oleksandr Vayda
Author-email: oleksandr.vayda@absa.africa
Requires-Python: >=3.9,<4.0
Classifier: License :: OSI Approved :: Apache Software License
Classifier: Operating System :: OS Independent
Classifier: Programming Language :: Python :: 3
Classifier: Programming Language :: Python :: 3.9
Classifier: Programming Language :: Python :: 3.10
Classifier: Programming Language :: Python :: 3.11
Classifier: Programming Language :: Python :: 3.9
Classifier: Topic :: Software Development :: Libraries
Requires-Dist: dynaconf (>=3.2.0,<4.0.0)
Requires-Dist: http-constants (>=0.5.0,<0.6.0)
Requires-Dist: requests (>=2.31.0,<3.0.0)
Project-URL: Repository, https://github.com/AbsaOSS/spline-python-agent
